README.md
setup.cfg
setup.py
4channel.egg-info/PKG-INFO
4channel.egg-info/SOURCES.txt
4channel.egg-info/dependency_links.txt
4channel.egg-info/entry_points.txt
4channel.egg-info/top_level.txt
fourchannel/__init__.py
fourchannel/__main__.py
fourchannel/fourchannel.py