Metadata-Version: 2.1
Name: 4channel
Version: 0.0.2
Summary: A python3 tool and module to download all images/webm from a 4channel thread.
Home-page: https://github.com/fatalhalt/fourchannel
Author: Kyle K
Author-email: kylek389@gmail.com
License: GPLv3
Keywords: 4chan,image,downloader,scraper
Platform: UNKNOWN
Classifier: Operating System :: POSIX :: Linux
Classifier: Operating System :: Microsoft :: Windows
Classifier: Intended Audience :: End Users/Desktop
Classifier: Topic :: Utilities
Classifier: License :: OSI Approved :: GNU General Public License v3 (GPLv3)
Classifier: Programming Language :: Python :: 3
Requires-Python: >=3.6
